[
  {
    "name": "Batman",
    "franchise": "DC Comics",
    "pack": {
      "type": "Starter",
      "name": "Starter Pack",
      "releaseWave": 1,
      "setNumber": "71200",
      "releaseDate": "2015"
    },
    "abilities": [
      "Boomerang",
      "Grapple",
      "Stealth"
    ],
    "voiceActor": "Troy Baker",
    "minifigure": {
      "legoId": "dim002",
      "imageUrl": "https://img.bricklink.com/ItemImage/MN/0/dim002.png",
      "dimensionsId": "dim002",
      "bricklinkId": "dim002",
      "imageUrls": [
        {
          "url": "https://img.bricklink.com/ItemImage/MN/0/dim002.png",
          "type": "minifig"
        }
      ]
    },
    "adventureWorld": "DC Comics",
    "aliases": [],
    "availabilityStatus": "unknown"
  },
  {
    "name": "Gandalf the Grey",
    "franchise": "The Lord of the Rings",
    "pack": {
      "type": "Starter",
      "name": "Starter Pack",
      "releaseWave": 1,
      "setNumber": "71200",
      "releaseDate": "2015"
    },
    "abilities": [
      "Illumination",
      "Magic",
      "Magic Shield",
      "MagicalShield"
    ],
    "voiceActor": "Tom Kane",
    "minifigure": {
      "legoId": "dim001",
      "imageUrl": "https://img.bricklink.com/ItemImage/MN/0/dim001.png",
      "dimensionsId": "dim001",
      "bricklinkId": "dim001",
      "imageUrls": [
        {
          "url": "https://img.bricklink.com/ItemImage/MN/0/dim001.png",
          "type": "minifig"
        }
      ]
    },
    "adventureWorld": "The Lord of the Rings",
    "aliases": [],
    "availabilityStatus": "unknown"
  },
  {
    "name": "Wyldstyle",
    "franchise": "The LEGO Movie",
    "pack": {
      "type": "Starter",
      "name": "Starter Pack",
      "releaseWave": 1,
      "setNumber": "71200",
      "releaseDate": "2015"
    },
    "abilities": [
      "Acrobat",
      "Master Build",
      "Relic Detector",
      "RelicDetector"
    ],
    "voiceActor": "Elizabeth Banks",
    "minifigure": {
      "legoId": "dim003",
      "imageUrl": "https://img.bricklink.com/ItemImage/MN/0/dim003.png",
      "dimensionsId": "dim003",
      "bricklinkId": "tlm099",
      "imageUrls": [
        {
          "url": "https://img.bricklink.com/ItemImage/MN/0/dim003.png",
          "type": "minifig"
        }
      ]
    },
    "adventureWorld": "The LEGO Movie",
    "aliases": [],
    "availabilityStatus": "unknown"
  },
  {
    "name": "Abby Yates",
    "franchise": "Ghostbusters (2016)",
    "pack": {
      "type": "Story",
      "name": "Ghostbusters (2016) Story Pack",
      "releaseWave": 2,
      "setNumber": "unknown",
      "releaseDate": "unknown"
    },
    "abilities": [
      "CharacterChanging",
      "HazardProtection",
      "Intelligence",
      "Laser",
      "Suspend Ghost"
    ],
    "voiceActor": "Melissa McCarthy",
    "minifigure": {
      "legoId": "dim033",
      "imageUrl": "https://img.bricklink.com/ItemImage/MN/0/dim033.png",
      "dimensionsId": "dim033",
      "bricklinkId": "unknown",
      "imageUrls": [
        {
          "url": "https://img.bricklink.com/ItemImage/MN/0/dim033.png",
          "type": "minifig"
        }
      ]
    },
    "adventureWorld": "unknown",
    "aliases": [],
    "availabilityStatus": "unknown"
  },
  {
    "name": "ACU Trooper",
    "franchise": "Jurassic World",
    "pack": {
      "type": "Team",
      "name": "Jurassic World Team Pack",
      "releaseWave": 1,
      "setNumber": "71205",
      "releaseDate": "unknown"
    },
    "abilities": [
      "Electricity",
      "Illumination"
    ],
    "voiceActor": "Robert Atkin Downes",
    "minifigure": {
      "legoId": "dim004",
      "imageUrl": "https://img.bricklink.com/ItemImage/MN/0/dim004.png",
      "dimensionsId": "dim004",
      "bricklinkId": "unknown",
      "imageUrls": [
        {
          "url": "https://img.bricklink.com/ItemImage/MN/0/dim004.png",
          "type": "minifig"
        }
      ]
    },
    "adventureWorld": "unknown",
    "aliases": [],
    "availabilityStatus": "unknown"
  },
  {
    "name": "Aquaman",
    "franchise": "DC Comics",
    "pack": {
      "type": "Fun",
      "name": "Aquaman Fun Pack",
      "releaseWave": 1,
      "setNumber": "71237",
      "releaseDate": "unknown"
    },
    "abilities": [
      "Atlantis",
      "Dive",
      "Growth",
      "Hazard Cleaner",
      "WaterSpray"
    ],
    "voiceActor": "Brian Bloom",
    "minifigure": {
      "legoId": "dim021",
      "imageUrl": "https://img.bricklink.com/ItemImage/MN/0/dim021.png",
      "dimensionsId": "dim021",
      "bricklinkId": "unknown",
      "imageUrls": [
        {
          "url": "https://img.bricklink.com/ItemImage/MN/0/dim021.png",
          "type": "minifig"
        }
      ]
    },
    "adventureWorld": "unknown",
    "aliases": [],
    "availabilityStatus": "unknown"
  },
  {
    "name": "B.A. Baracus",
    "franchise": "The A-Team",
    "pack": {
      "type": "unknown",
      "name": "A-Team Fun Pack",
      "releaseWave": 6,
      "setNumber": "71251",
      "releaseDate": "2016"
    },
    "abilities": [
      "A-Team Master Build",
      "A-Team Master Build (Uniek)",
      "Fix-It",
      "Silver LEGO Blowup",
      "Super Strength",
      "SuperStrength",
      "Target"
    ],
    "voiceActor": "unknown",
    "minifigure": {
      "legoId": null,
      "imageUrl": "https://img.bricklink.com/ItemImage/MN/0/dim024.png",
      "dimensionsId": "unknown",
      "bricklinkId": "dim024",
      "imageUrls": [
        {
          "url": "https://img.bricklink.com/ItemImage/MN/0/dim024.png",
          "type": "minifig"
        }
      ]
    },
    "adventureWorld": "The A-Team",
    "aliases": [],
    "availabilityStatus": "unknown"
  },
  {
    "name": "Bad Cop",
    "franchise": "The LEGO Movie",
    "pack": {
      "type": "Fun",
      "name": "Bad Cop Fun Pack",
      "releaseWave": 1,
      "setNumber": "71213",
      "releaseDate": "unknown"
    },
    "abilities": [
      "Laser",
      "Relic Detector",
      "Target"
    ],
    "voiceActor": "Liam Neeson",
    "minifigure": {
      "legoId": "dim007",
      "imageUrl": "https://img.bricklink.com/ItemImage/MN/0/dim007.png",
      "dimensionsId": "dim007",
      "bricklinkId": "unknown",
      "imageUrls": [
        {
          "url": "https://img.bricklink.com/ItemImage/MN/0/dim007.png",
          "type": "minifig"
        }
      ]
    },
    "adventureWorld": "unknown",
    "aliases": [],
    "availabilityStatus": "unknown"
  },
  {
    "name": "Bane",
    "franchise": "DC Comics",
    "pack": {
      "type": "Fun",
      "name": "Bane Fun Pack",
      "releaseWave": 1,
      "setNumber": "71240",
      "releaseDate": "unknown"
    },
    "abilities": [
      "Big Transform",
      "BigTransform",
      "Hazard Protection",
      "Super Strength",
      "SuperStrength"
    ],
    "voiceActor": "Steve Blum",
    "minifigure": {
      "legoId": "dim022",
      "imageUrl": "https://img.bricklink.com/ItemImage/MN/0/dim022.png",
      "dimensionsId": "dim022",
      "bricklinkId": "unknown",
      "imageUrls": [
        {
          "url": "https://img.bricklink.com/ItemImage/MN/0/dim022.png",
          "type": "minifig"
        }
      ]
    },
    "adventureWorld": "unknown",
    "aliases": [],
    "availabilityStatus": "unknown"
  },
  {
    "name": "Bart Simpson",
    "franchise": "The Simpsons",
    "pack": {
      "type": "Fun",
      "name": "Bart Fun Pack",
      "releaseWave": 1,
      "setNumber": "unknown",
      "releaseDate": "unknown"
    },
    "abilities": [
      "Mini Access",
      "Target"
    ],
    "voiceActor": "unknown",
    "minifigure": {
      "legoId": "dim015",
      "imageUrl": "https://img.bricklink.com/ItemImage/MN/0/dim015.png",
      "dimensionsId": "dim015",
      "bricklinkId": "unknown",
      "imageUrls": [
        {
          "url": "https://img.bricklink.com/ItemImage/MN/0/dim015.png",
          "type": "minifig"
        }
      ]
    },
    "adventureWorld": "unknown",
    "aliases": [],
    "availabilityStatus": "unknown"
  },
  {
    "name": "Batgirl",
    "franchise": "The LEGO Batman Movie",
    "pack": {
      "type": "Story",
      "name": "The LEGO Batman Movie Story Pack",
      "releaseWave": 2,
      "setNumber": "71264",
      "releaseDate": "unknown"
    },
    "abilities": [
      "Acrobat",
      "Boomerang"
    ],
    "voiceActor": "Rosario Dawson",
    "minifigure": {
      "legoId": "dim044",
      "imageUrl": "https://img.bricklink.com/ItemImage/MN/0/dim044.png",
      "dimensionsId": "dim044",
      "bricklinkId": "unknown",
      "imageUrls": [
        {
          "url": "https://img.bricklink.com/ItemImage/MN/0/dim044.png",
          "type": "minifig"
        }
      ]
    },
    "adventureWorld": "unknown",
    "aliases": [],
    "availabilityStatus": "unknown"
  },
  {
    "name": "Beast Boy",
    "franchise": "Teen Titans Go!",
    "pack": {
      "type": "unknown",
      "name": "Teen Titans Go! Team Pack",
      "releaseWave": 9,
      "setNumber": "71255",
      "releaseDate": "2017"
    },
    "abilities": [
      "Dive",
      "Mini Access",
      "Mini Access)",
      "Tracking",
      "Transformation (Flight"
    ],
    "voiceActor": "unknown",
    "minifigure": {
      "legoId": null,
      "imageUrl": "https://img.bricklink.com/ItemImage/MN/0/dim049.png",
      "dimensionsId": "unknown",
      "bricklinkId": "dim049",
      "imageUrls": [
        {
          "url": "https://img.bricklink.com/ItemImage/MN/0/dim049.png",
          "type": "minifig"
        }
      ]
    },
    "adventureWorld": "Teen Titans Go!",
    "aliases": [],
    "availabilityStatus": "unknown"
  },
  {
    "name": "Betelgeuse",
    "franchise": "Beetlejuice",
    "pack": {
      "type": "Fun",
      "name": "Beetlejuice Fun Pack",
      "releaseWave": 2,
      "setNumber": "71349",
      "releaseDate": "unknown"
    },
    "abilities": [
      "Magic",
      "MindControl"
    ],
    "voiceActor": "Christopher Swindle",
    "minifigure": {
      "legoId": "dim051",
      "imageUrl": "https://img.bricklink.com/ItemImage/MN/0/dim051.png",
      "dimensionsId": "dim051",
      "bricklinkId": "unknown",
      "imageUrls": [
        {
          "url": "https://img.bricklink.com/ItemImage/MN/0/dim051.png",
          "type": "minifig"
        }
      ]
    },
    "aliases": [
      "Beetlejuice"
    ],
    "adventureWorld": "unknown",
    "availabilityStatus": "unknown"
  },
  {
    "name": "Benny",
    "franchise": "The LEGO Movie",
    "pack": {
      "type": "Fun",
      "name": "Benny Fun Pack",
      "releaseWave": 1,
      "setNumber": "71214",
      "releaseDate": "unknown"
    },
    "abilities": [
      "Glide",
      "Hacking",
      "Master Build",
      "Sonar Smash",
      "SonarSmash",
      "Target",
      "Technology"
    ],
    "voiceActor": "Charlie Day",
    "minifigure": {
      "legoId": "dim008",
      "imageUrl": "https://img.bricklink.com/ItemImage/MN/0/dim008.png",
      "dimensionsId": "dim008",
      "bricklinkId": "unknown",
      "imageUrls": [
        {
          "url": "https://img.bricklink.com/ItemImage/MN/0/dim008.png",
          "type": "minifig"
        }
      ]
    },
    "adventureWorld": "unknown",
    "aliases": [],
    "availabilityStatus": "unknown"
  },
  {
    "name": "Blossom",
    "franchise": "The Powerpuff Girls",
    "pack": {
      "type": "Team",
      "name": "The Powerpuff Girls Team Pack",
      "releaseWave": 2,
      "setNumber": "71346",
      "releaseDate": "unknown"
    },
    "abilities": [
      "Flying",
      "Rainbow LEGO Objects"
    ],
    "voiceActor": "Amanda Leighton",
    "minifigure": {
      "legoId": "dim052",
      "imageUrl": "https://img.bricklink.com/ItemImage/MN/0/dim052.png",
      "dimensionsId": "dim052",
      "bricklinkId": "unknown",
      "imageUrls": [
        {
          "url": "https://img.bricklink.com/ItemImage/MN/0/dim052.png",
          "type": "minifig"
        }
      ]
    },
    "adventureWorld": "unknown",
    "aliases": [],
    "availabilityStatus": "unknown"
  },
  {
    "name": "Bubbles",
    "franchise": "The Powerpuff Girls",
    "pack": {
      "type": "Team",
      "name": "The Powerpuff Girls Team Pack",
      "releaseWave": 2,
      "setNumber": "71346",
      "releaseDate": "unknown"
    },
    "abilities": [
      "Flight",
      "Flying",
      "HeartRegeneration",
      "Laser",
      "RainbowLEGOObjects",
      "SuperStrength"
    ],
    "voiceActor": "Kristen Li",
    "minifigure": {
      "legoId": "dim053",
      "imageUrl": "https://img.bricklink.com/ItemImage/MN/0/dim053.png",
      "dimensionsId": "dim053",
      "bricklinkId": "unknown",
      "imageUrls": [
        {
          "url": "https://img.bricklink.com/ItemImage/MN/0/dim053.png",
          "type": "minifig"
        }
      ]
    },
    "adventureWorld": "unknown",
    "aliases": [],
    "availabilityStatus": "unknown"
  },
  {
    "name": "Buttercup",
    "franchise": "The Powerpuff Girls",
    "pack": {
      "type": "Fun",
      "name": "The Powerpuff Girls Fun Pack",
      "releaseWave": 2,
      "setNumber": "71343",
      "releaseDate": "unknown"
    },
    "abilities": [
      "Flying",
      "Super Strength"
    ],
    "voiceActor": "Natalie Palamides",
    "minifigure": {
      "legoId": "dim054",
      "imageUrl": "https://img.bricklink.com/ItemImage/MN/0/dim054.png",
      "dimensionsId": "dim054",
      "bricklinkId": "unknown",
      "imageUrls": [
        {
          "url": "https://img.bricklink.com/ItemImage/MN/0/dim054.png",
          "type": "minifig"
        }
      ]
    },
    "adventureWorld": "unknown",
    "aliases": [],
    "availabilityStatus": "unknown"
  },
  {
    "name": "Chase McCain",
    "franchise": "LEGO City",
    "pack": {
      "type": "Fun",
      "name": "LEGO City Fun Pack",
      "releaseWave": 2,
      "setNumber": "71266",
      "releaseDate": "unknown"
    },
    "abilities": [
      "Acrobat",
      "Drill",
      "Glide",
      "Grapple",
      "Hacking",
      "Relic Detector",
      "RelicDetector",
      "Target",
      "Tracking",
      "WaterSpray"
    ],
    "voiceActor": "Joseph May",
    "minifigure": {
      "legoId": "dim042",
      "imageUrl": "https://img.bricklink.com/ItemImage/MN/0/dim042.png",
      "dimensionsId": "dim042",
      "bricklinkId": "unknown",
      "imageUrls": [
        {
          "url": "https://img.bricklink.com/ItemImage/MN/0/dim042.png",
          "type": "minifig"
        }
      ]
    },
    "adventureWorld": "unknown",
    "aliases": [],
    "availabilityStatus": "unknown"
  },
  {
    "name": "Chell",
    "franchise": "Portal 2",
    "pack": {
      "type": "Level",
      "name": "Portal 2 Level Pack",
      "releaseWave": 1,
      "setNumber": "71203",
      "releaseDate": "2015"
    },
    "abilities": [
      "Acrobat",
      "Portal Gun",
      "Portal Gun (Uniek)",
      "PortalGun"
    ],
    "voiceActor": "unknown",
    "minifigure": {
      "legoId": "dim005",
      "imageUrl": "https://img.bricklink.com/ItemImage/MN/0/dim005.png",
      "dimensionsId": "dim005",
      "bricklinkId": "dim006",
      "imageUrls": [
        {
          "url": "https://img.bricklink.com/ItemImage/MN/0/dim005.png",
          "type": "minifig"
        }
      ]
    },
    "adventureWorld": "Portal 2",
    "aliases": [],
    "availabilityStatus": "unknown"
  },
  {
    "name": "Cole",
    "franchise": "Ninjago",
    "pack": {
      "type": "Team",
      "name": "LEGO Ninjago Team Pack",
      "releaseWave": 1,
      "setNumber": "71207",
      "releaseDate": "unknown"
    },
    "abilities": [
      "Acrobat",
      "Spinjitzu",
      "Stealth",
      "Super Strength"
    ],
    "voiceActor": "Kirby Morrow",
    "minifigure": {
      "legoId": "dim013",
      "imageUrl": "https://img.bricklink.com/ItemImage/MN/0/dim013.png",
      "dimensionsId": "dim013",
      "bricklinkId": "unknown",
      "imageUrls": [
        {
          "url": "https://img.bricklink.com/ItemImage/MN/0/dim013.png",
          "type": "minifig"
        }
      ]
    },
    "adventureWorld": "unknown",
    "aliases": [],
    "availabilityStatus": "unknown"
  },
  {
    "name": "Cragger",
    "franchise": "Legends of Chima",
    "pack": {
      "type": "Fun",
      "name": "Cragger Fun Pack",
      "releaseWave": 1,
      "setNumber": "71223",
      "releaseDate": "unknown"
    },
    "abilities": [
      "Acrobat",
      "CHI",
      "Dive",
      "Hazard Protection",
      "Super Strength"
    ],
    "voiceActor": "David Attar",
    "minifigure": {
      "legoId": "dim018",
      "imageUrl": "https://img.bricklink.com/ItemImage/MN/0/dim018.png",
      "dimensionsId": "dim018",
      "bricklinkId": "unknown",
      "imageUrls": [
        {
          "url": "https://img.bricklink.com/ItemImage/MN/0/dim018.png",
          "type": "minifig"
        }
      ]
    },
    "adventureWorld": "unknown",
    "aliases": [],
    "availabilityStatus": "unknown"
  },
  {
    "name": "Cyberman",
    "franchise": "Doctor Who",
    "pack": {
      "type": "Fun",
      "name": "Cyberman Fun Pack",
      "releaseWave": 1,
      "setNumber": "unknown",
      "releaseDate": "unknown"
    },
    "abilities": [
      "Dive",
      "Drone",
      "Hacking",
      "Laser",
      "Mind Control",
      "Silver LEGO Blowup",
      "SilverLEGODestruction",
      "Technology",
      "X-Ray Vision",
      "XRayVision"
    ],
    "voiceActor": "Nicholas Briggs",
    "minifigure": {
      "legoId": "dim023",
      "imageUrl": "https://img.bricklink.com/ItemImage/MN/0/dim023.png",
      "dimensionsId": "dim023",
      "bricklinkId": "unknown",
      "imageUrls": [
        {
          "url": "https://img.bricklink.com/ItemImage/MN/0/dim023.png",
          "type": "minifig"
        }
      ]
    },
    "adventureWorld": "unknown",
    "aliases": [],
    "availabilityStatus": "unknown"
  },
  {
    "name": "Cyborg",
    "franchise": "DC Comics",
    "pack": {
      "type": "Fun",
      "name": "Cyborg Fun Pack",
      "releaseWave": 1,
      "setNumber": "71210",
      "releaseDate": "unknown"
    },
    "abilities": [
      "Big Transform",
      "BigTransform",
      "Dive",
      "Laser",
      "Super Strength",
      "SuperStrength",
      "Target",
      "Technology"
    ],
    "voiceActor": "Bumper Robinson",
    "minifigure": {
      "legoId": "dim006",
      "imageUrl": "https://img.bricklink.com/ItemImage/MN/0/dim006.png",
      "dimensionsId": "dim006",
      "bricklinkId": "unknown",
      "imageUrls": [
        {
          "url": "https://img.bricklink.com/ItemImage/MN/0/dim006.png",
          "type": "minifig"
        }
      ]
    },
    "adventureWorld": "unknown",
    "aliases": [],
    "availabilityStatus": "unknown"
  },
  {
    "name": "Doc Brown",
    "franchise": "Back to the Future",
    "pack": {
      "type": "Fun",
      "name": "Doc Brown Fun Pack",
      "releaseWave": 1,
      "setNumber": "71230",
      "releaseDate": "unknown"
    },
    "abilities": [
      "Drone",
      "Fix-It",
      "FixIt",
      "Hacking",
      "Intelligence",
      "Technology"
    ],
    "voiceActor": "Christopher Lloyd",
    "minifigure": {
      "legoId": "dim024",
      "imageUrl": "https://img.bricklink.com/ItemImage/MN/0/dim024.png",
      "dimensionsId": "dim024",
      "bricklinkId": "unknown",
      "imageUrls": [
        {
          "url": "https://img.bricklink.com/ItemImage/MN/0/dim024.png",
          "type": "minifig"
        }
      ]
    },
    "adventureWorld": "unknown",
    "aliases": [],
    "availabilityStatus": "unknown"
  },
  {
    "name": "The Doctor",
    "franchise": "Doctor Who",
    "pack": {
      "type": "Level",
      "name": "Doctor Who Level Pack",
      "releaseWave": 2,
      "setNumber": "71204",
      "releaseDate": "2015"
    },
    "abilities": [
      "CharacterChanging",
      "Fix-It",
      "FixIt",
      "Hacking",
      "Illumination",
      "Intelligence",
      "MiniAccess",
      "Sonar Smash",
      "SonarSmash",
      "TARDIS Travel (Uniek)",
      "Technology"
    ],
    "voiceActor": "Peter Capaldi",
    "minifigure": {
      "legoId": "dim011pb01",
      "imageUrl": "https://img.bricklink.com/ItemImage/MN/0/dim011pb01.png",
      "dimensionsId": "dim011pb01",
      "bricklinkId": "dim009",
      "imageUrls": [
        {
          "url": "https://img.bricklink.com/ItemImage/MN/0/dim011pb01.png",
          "type": "minifig"
        }
      ]
    },
    "adventureWorld": "Doctor Who",
    "aliases": [],
    "availabilityStatus": "unknown"
  },
  {
    "name": "Emmet",
    "franchise": "The LEGO Movie",
    "pack": {
      "type": "Fun",
      "name": "Emmet Fun Pack",
      "releaseWave": 1,
      "setNumber": "71212",
      "releaseDate": "unknown"
    },
    "abilities": [
      "Drill",
      "Fix-It",
      "FixIt",
      "Master Build"
    ],
    "voiceActor": "Chris Pratt",
    "minifigure": {
      "legoId": "dim009",
      "imageUrl": "https://img.bricklink.com/ItemImage/MN/0/dim009.png",
      "dimensionsId": "dim009",
      "bricklinkId": "unknown",
      "imageUrls": [
        {
          "url": "https://img.bricklink.com/ItemImage/MN/0/dim009.png",
          "type": "minifig"
        }
      ]
    },
    "adventureWorld": "unknown",
    "aliases": [],
    "availabilityStatus": "unknown"
  },
  {
    "name": "Eris",
    "franchise": "Legends of Chima",
    "pack": {
      "type": "Fun",
      "name": "Eris Fun Pack",
      "releaseWave": 1,
      "setNumber": "71232",
      "releaseDate": "unknown"
    },
    "abilities": [
      "CHI",
      "Flight",
      "Flying",
      "Super Strength",
      "SuperStrength",
      "Target"
    ],
    "voiceActor": "Bethany Brown",
    "minifigure": {
      "legoId": "dim019",
      "imageUrl": "https://img.bricklink.com/ItemImage/MN/0/dim019.png",
      "dimensionsId": "dim019",
      "bricklinkId": "unknown",
      "imageUrls": [
        {
          "url": "https://img.bricklink.com/ItemImage/MN/0/dim019.png",
          "type": "minifig"
        }
      ]
    },
    "adventureWorld": "unknown",
    "aliases": [],
    "availabilityStatus": "unknown"
  },
  {
    "name": "E.T.",
    "franchise": "E.T.",
    "pack": {
      "type": "Fun",
      "name": "E.T. Fun Pack",
      "releaseWave": 2,
      "setNumber": "unknown",
      "releaseDate": "unknown"
    },
    "abilities": [
      "Flying",
      "Growth",
      "Mini Access"
    ],
    "voiceActor": "unknown",
    "minifigure": {
      "legoId": "dim038",
      "imageUrl": "https://img.bricklink.com/ItemImage/MN/0/dim038.png",
      "dimensionsId": "dim038",
      "bricklinkId": "unknown",
      "imageUrls": [
        {
          "url": "https://img.bricklink.com/ItemImage/MN/0/dim038.png",
          "type": "minifig"
        }
      ]
    },
    "adventureWorld": "unknown",
    "aliases": [],
    "availabilityStatus": "unknown"
  },
  {
    "name": "Ethan Hunt",
    "franchise": "Mission: Impossible",
    "pack": {
      "type": "Level",
      "name": "Mission: Impossible Level Pack",
      "releaseWave": 2,
      "setNumber": "unknown",
      "releaseDate": "unknown"
    },
    "abilities": [
      "Acrobat",
      "Dive",
      "Drone",
      "Grapple",
      "Stealth",
      "Technology",
      "X-Ray Vision"
    ],
    "voiceActor": "unknown",
    "minifigure": {
      "legoId": "dim028",
      "imageUrl": "https://img.bricklink.com/ItemImage/MN/0/dim028.png",
      "dimensionsId": "dim028",
      "bricklinkId": "unknown",
      "imageUrls": [
        {
          "url": "https://img.bricklink.com/ItemImage/MN/0/dim028.png",
          "type": "minifig"
        }
      ]
    },
    "adventureWorld": "unknown",
    "aliases": [],
    "availabilityStatus": "unknown"
  },
  {
    "name": "Excalibur Batman",
    "franchise": "The LEGO Batman Movie",
    "pack": {
      "type": "Fun",
      "name": "Excalibur Batman Fun Pack",
      "releaseWave": 2,
      "setNumber": "unknown",
      "releaseDate": "unknown"
    },
    "abilities": [
      "Boomerang",
      "Grapple",
      "LaserDeflector",
      "Stealth",
      "SuperStrength",
      "SwordSwitch"
    ],
    "voiceActor": "Will Arnett",
    "minifigure": {
      "legoId": "dim043",
      "imageUrl": "https://img.bricklink.com/ItemImage/MN/0/dim043.png",
      "dimensionsId": "dim043",
      "bricklinkId": "unknown",
      "imageUrls": [
        {
          "url": "https://img.bricklink.com/ItemImage/MN/0/dim043.png",
          "type": "minifig"
        }
      ]
    },
    "adventureWorld": "unknown",
    "aliases": [],
    "availabilityStatus": "unknown"
  },
  {
    "name": "Finn the Human",
    "franchise": "Adventure Time",
    "pack": {
      "type": "Level",
      "name": "Adventure Time Level Pack",
      "releaseWave": 2,
      "setNumber": "71245",
      "releaseDate": "unknown"
    },
    "abilities": [
      "Acrobat"
    ],
    "voiceActor": "Jeremy Shada",
    "minifigure": {
      "legoId": "dim026",
      "imageUrl": "https://img.bricklink.com/ItemImage/MN/0/dim026.png",
      "dimensionsId": "dim026",
      "bricklinkId": "unknown",
      "imageUrls": [
        {
          "url": "https://img.bricklink.com/ItemImage/MN/0/dim026.png",
          "type": "minifig"
        }
      ]
    },
    "adventureWorld": "unknown",
    "aliases": [],
    "availabilityStatus": "unknown"
  },
  {
    "name": "Gamer Kid",
    "franchise": "Midway Arcade",
    "pack": {
      "type": "Level",
      "name": "Midway Arcade Level Pack",
      "releaseWave": 1,
      "setNumber": "unknown",
      "releaseDate": "unknown"
    },
    "abilities": [
      "Invulnerability",
      "Laser",
      "Speed",
      "Stealth",
      "SuperStrength"
    ],
    "voiceActor": "Josh Keaton",
    "minifigure": {
      "legoId": "dim025",
      "imageUrl": "https://img.bricklink.com/ItemImage/MN/0/dim025.png",
      "dimensionsId": "dim025",
      "bricklinkId": "unknown",
      "imageUrls": [
        {
          "url": "https://img.bricklink.com/ItemImage/MN/0/dim025.png",
          "type": "minifig"
        }
      ]
    },
    "adventureWorld": "unknown",
    "aliases": [],
    "availabilityStatus": "unknown"
  },
  {
    "name": "Gimli",
    "franchise": "The Lord of the Rings",
    "pack": {
      "type": "Fun",
      "name": "Gimli Fun Pack",
      "releaseWave": 1,
      "setNumber": "71220",
      "releaseDate": "unknown"
    },
    "abilities": [
      "Mini Access",
      "Super Strength",
      "SuperStrength"
    ],
    "voiceActor": "John Rhys-Davies",
    "minifigure": {
      "legoId": "dim014",
      "imageUrl": "https://img.bricklink.com/ItemImage/MN/0/dim014.png",
      "dimensionsId": "dim014",
      "bricklinkId": "unknown",
      "imageUrls": [
        {
          "url": "https://img.bricklink.com/ItemImage/MN/0/dim014.png",
          "type": "minifig"
        }
      ]
    },
    "adventureWorld": "unknown",
    "aliases": [],
    "availabilityStatus": "unknown"
  },
  {
    "name": "Gizmo",
    "franchise": "Gremlins",
    "pack": {
      "type": "Team",
      "name": "Gremlins Team Pack",
      "releaseWave": 2,
      "setNumber": "71256",
      "releaseDate": "unknown"
    },
    "abilities": [
      "Acrobat"
    ],
    "voiceActor": "Howie Mandel",
    "minifigure": {
      "legoId": "dim036",
      "imageUrl": "https://img.bricklink.com/ItemImage/MN/0/dim036.png",
      "dimensionsId": "dim036",
      "bricklinkId": "unknown",
      "imageUrls": [
        {
          "url": "https://img.bricklink.com/ItemImage/MN/0/dim036.png",
          "type": "minifig"
        }
      ]
    },
    "adventureWorld": "unknown",
    "aliases": [],
    "availabilityStatus": "unknown"
  },
  {
    "name": "Gollum",
    "franchise": "The Lord of the Rings",
    "pack": {
      "type": "Fun",
      "name": "Gollum Fun Pack",
      "releaseWave": 1,
      "setNumber": "71218",
      "releaseDate": "unknown"
    },
    "abilities": [
      "Acrobat",
      "Boomerang",
      "Dive",
      "Magic",
      "Mini Access",
      "Silver LEGO Blowup"
    ],
    "voiceActor": "Liam O'Brien",
    "minifigure": {
      "legoId": "dim012",
      "imageUrl": "https://img.bricklink.com/ItemImage/MN/0/dim012.png",
      "dimensionsId": "dim012",
      "bricklinkId": "unknown",
      "imageUrls": [
        {
          "url": "https://img.bricklink.com/ItemImage/MN/0/dim012.png",
          "type": "minifig"
        }
      ]
    },
    "adventureWorld": "unknown",
    "aliases": [],
    "availabilityStatus": "unknown"
  },
  {
    "name": "Harley Quinn",
    "franchise": "DC Comics",
    "pack": {
      "type": "Team",
      "name": "DC Comics Team Pack",
      "releaseWave": 1,
      "setNumber": "71229",
      "releaseDate": "unknown"
    },
    "abilities": [
      "Acrobat",
      "Super Strength",
      "SuperStrength"
    ],
    "voiceActor": "Tara Strong",
    "minifigure": {
      "legoId": "dim020",
      "imageUrl": "https://img.bricklink.com/ItemImage/MN/0/dim020.png",
      "dimensionsId": "dim020",
      "bricklinkId": "unknown",
      "imageUrls": [
        {
          "url": "https://img.bricklink.com/ItemImage/MN/0/dim020.png",
          "type": "minifig"
        }
      ]
    },
    "adventureWorld": "unknown",
    "aliases": [],
    "availabilityStatus": "unknown"
  },
  {
    "name": "Harry Potter",
    "franchise": "Harry Potter",
    "pack": {
      "type": "Team",
      "name": "Harry Potter Team Pack",
      "releaseWave": 2,
      "setNumber": "71247",
      "releaseDate": "unknown"
    },
    "abilities": [
      "Flight",
      "Growth",
      "HazardCleaner",
      "Illumination",
      "Intelligence",
      "Magic",
      "MagicalShield",
      "SilverLEGODestruction",
      "Target"
    ],
    "voiceActor": "Daniel Radcliffe",
    "minifigure": {
      "legoId": "dim031",
      "imageUrl": "https://img.bricklink.com/ItemImage/MN/0/dim031.png",
      "dimensionsId": "dim031",
      "bricklinkId": "unknown",
      "imageUrls": [
        {
          "url": "https://img.bricklink.com/ItemImage/MN/0/dim031.png",
          "type": "minifig"
        }
      ]
    },
    "adventureWorld": "unknown",
    "aliases": [],
    "availabilityStatus": "unknown"
  },
  {
    "name": "Hermione Granger",
    "franchise": "Harry Potter",
    "pack": {
      "type": "Fun",
      "name": "Hermione Fun Pack",
      "releaseWave": 2,
      "setNumber": "71243",
      "releaseDate": "unknown"
    },
    "abilities": [
      "Acrobat",
      "Magic"
    ],
    "voiceActor": "Emma Watson",
    "minifigure": {
      "legoId": null,
      "imageUrl": "unknown",
      "dimensionsId": "unknown",
      "bricklinkId": "unknown",
      "imageUrls": []
    },
    "adventureWorld": "unknown",
    "aliases": [],
    "availabilityStatus": "unknown"
  },
  {
    "name": "Homer Simpson",
    "franchise": "The Simpsons",
    "pack": {
      "type": "Level",
      "name": "The Simpsons Level Pack",
      "releaseWave": 1,
      "setNumber": "71202",
      "releaseDate": "unknown"
    },
    "abilities": [
      "Big Transform",
      "BigTransform",
      "SuperStrength"
    ],
    "voiceActor": "Dan Castellaneta",
    "minifigure": {
      "legoId": "dim009pb01",
      "imageUrl": "https://img.bricklink.com/ItemImage/MN/0/dim009pb01.png",
      "dimensionsId": "dim009pb01",
      "bricklinkId": "unknown",
      "imageUrls": [
        {
          "url": "https://img.bricklink.com/ItemImage/MN/0/dim009pb01.png",
          "type": "minifig"
        }
      ]
    },
    "adventureWorld": "unknown",
    "aliases": [],
    "availabilityStatus": "unknown"
  },
  {
    "name": "Jake the Dog",
    "franchise": "Adventure Time",
    "pack": {
      "type": "Team",
      "name": "Adventure Time Team Pack",
      "releaseWave": 2,
      "setNumber": "71246",
      "releaseDate": "unknown"
    },
    "abilities": [
      "BigTransform",
      "SuperStrength"
    ],
    "voiceActor": "John DiMaggio",
    "minifigure": {
      "legoId": "dim027",
      "imageUrl": "https://img.bricklink.com/ItemImage/MN/0/dim027.png",
      "dimensionsId": "dim027",
      "bricklinkId": "unknown",
      "imageUrls": [
        {
          "url": "https://img.bricklink.com/ItemImage/MN/0/dim027.png",
          "type": "minifig"
        }
      ]
    },
    "adventureWorld": "unknown",
    "aliases": [],
    "availabilityStatus": "unknown"
  },
  {
    "name": "Jay",
    "franchise": "Ninjago",
    "pack": {
      "type": "Fun",
      "name": "Jay Fun Pack",
      "releaseWave": 1,
      "setNumber": "71215",
      "releaseDate": "unknown"
    },
    "abilities": [
      "Acrobat",
      "Electricity",
      "Fix-It",
      "LaserDeflector",
      "Spinjitzu",
      "Stealth"
    ],
    "voiceActor": "Michael Adamthwaite",
    "minifigure": {
      "legoId": "dim017",
      "imageUrl": "https://img.bricklink.com/ItemImage/MN/0/dim017.png",
      "dimensionsId": "dim017",
      "bricklinkId": "unknown",
      "imageUrls": [
        {
          "url": "https://img.bricklink.com/ItemImage/MN/0/dim017.png",
          "type": "minifig"
        }
      ]
    },
    "adventureWorld": "unknown",
    "aliases": [],
    "availabilityStatus": "unknown"
  },
  {
    "name": "The Joker",
    "franchise": "DC Comics",
    "pack": {
      "type": "Team",
      "name": "DC Comics Team Pack",
      "releaseWave": 1,
      "setNumber": "71229",
      "releaseDate": "unknown"
    },
    "abilities": [
      "Electricity",
      "Grapple",
      "Hazard Protection",
      "Target"
    ],
    "voiceActor": "Christopher Corey Smith",
    "minifigure": {
      "legoId": "dim019",
      "imageUrl": "https://img.bricklink.com/ItemImage/MN/0/dim019.png",
      "dimensionsId": "dim019",
      "bricklinkId": "unknown",
      "imageUrls": [
        {
          "url": "https://img.bricklink.com/ItemImage/MN/0/dim019.png",
          "type": "minifig"
        }
      ]
    },
    "adventureWorld": "unknown",
    "aliases": [],
    "availabilityStatus": "unknown"
  },
  {
    "name": "Kai",
    "franchise": "Ninjago",
    "pack": {
      "type": "Team",
      "name": "LEGO Ninjago Team Pack",
      "releaseWave": 1,
      "setNumber": "71239",
      "releaseDate": "unknown"
    },
    "abilities": [
      "Acrobat",
      "Spinjitzu",
      "Stealth"
    ],
    "voiceActor": "Vincent Tong",
    "minifigure": {
      "legoId": "dim012pb01",
      "imageUrl": "https://img.bricklink.com/ItemImage/MN/0/dim012pb01.png",
      "dimensionsId": "dim012pb01",
      "bricklinkId": "unknown",
      "imageUrls": [
        {
          "url": "https://img.bricklink.com/ItemImage/MN/0/dim012pb01.png",
          "type": "minifig"
        }
      ]
    },
    "adventureWorld": "unknown",
    "aliases": [],
    "availabilityStatus": "unknown"
  },
  {
    "name": "Krusty the Clown",
    "franchise": "The Simpsons",
    "pack": {
      "type": "Fun",
      "name": "Krusty Fun Pack",
      "releaseWave": 1,
      "setNumber": "unknown",
      "releaseDate": "unknown"
    },
    "abilities": [
      "Growth",
      "HazardCleaner",
      "Target",
      "WaterSpray"
    ],
    "voiceActor": "Dan Castellaneta",
    "minifigure": {
      "legoId": "dim016",
      "imageUrl": "https://img.bricklink.com/ItemImage/MN/0/dim016.png",
      "dimensionsId": "dim016",
      "bricklinkId": "unknown",
      "imageUrls": [
        {
          "url": "https://img.bricklink.com/ItemImage/MN/0/dim016.png",
          "type": "minifig"
        }
      ]
    },
    "adventureWorld": "unknown",
    "aliases": [],
    "availabilityStatus": "unknown"
  },
  {
    "name": "Laval",
    "franchise": "Legends of Chima",
    "pack": {
      "type": "Fun",
      "name": "Laval Fun Pack",
      "releaseWave": 1,
      "setNumber": "unknown",
      "releaseDate": "unknown"
    },
    "abilities": [
      "Acrobat",
      "CHI",
      "Sonar Smash",
      "Super Strength",
      "Target"
    ],
    "voiceActor": "Scott Shantz",
    "minifigure": {
      "legoId": "dim017pb01",
      "imageUrl": "https://img.bricklink.com/ItemImage/MN/0/dim017pb01.png",
      "dimensionsId": "dim017pb01",
      "bricklinkId": "unknown",
      "imageUrls": [
        {
          "url": "https://img.bricklink.com/ItemImage/MN/0/dim017pb01.png",
          "type": "minifig"
        }
      ]
    },
    "adventureWorld": "unknown",
    "aliases": [],
    "availabilityStatus": "unknown"
  },
  {
    "name": "Legolas",
    "franchise": "The Lord of the Rings",
    "pack": {
      "type": "Fun",
      "name": "Legolas Fun Pack",
      "releaseWave": 1,
      "setNumber": "71219",
      "releaseDate": "unknown"
    },
    "abilities": [
      "Acrobat",
      "GrindRails",
      "Magic",
      "Pole Vault",
      "Target"
    ],
    "voiceActor": "Orlando Bloom",
    "minifigure": {
      "legoId": "dim013pb01",
      "imageUrl": "https://img.bricklink.com/ItemImage/MN/0/dim013pb01.png",
      "dimensionsId": "dim013pb01",
      "bricklinkId": "unknown",
      "imageUrls": [
        {
          "url": "https://img.bricklink.com/ItemImage/MN/0/dim013pb01.png",
          "type": "minifig"
        }
      ]
    },
    "adventureWorld": "unknown",
    "aliases": [],
    "availabilityStatus": "unknown"
  },
  {
    "name": "Lloyd",
    "franchise": "Ninjago",
    "pack": {
      "type": "Fun",
      "name": "Lloyd Fun Pack",
      "releaseWave": 1,
      "setNumber": "unknown",
      "releaseDate": "unknown"
    },
    "abilities": [
      "Acrobat",
      "Illumination",
      "Spinjitzu",
      "Stealth"
    ],
    "voiceActor": "Jillian Michaels",
    "minifigure": {
      "legoId": "dim023pb01",
      "imageUrl": "https://img.bricklink.com/ItemImage/MN/0/dim023pb01.png",
      "dimensionsId": "dim023pb01",
      "bricklinkId": "unknown",
      "imageUrls": [
        {
          "url": "https://img.bricklink.com/ItemImage/MN/0/dim023pb01.png",
          "type": "minifig"
        }
      ]
    },
    "adventureWorld": "unknown",
    "aliases": [],
    "availabilityStatus": "unknown"
  },
  {
    "name": "Lord Voldemort",
    "franchise": "Harry Potter",
    "pack": {
      "type": "Team",
      "name": "Harry Potter Team Pack",
      "releaseWave": 2,
      "setNumber": "71247",
      "releaseDate": "unknown"
    },
    "abilities": [
      "Flight",
      "Growth",
      "HazardCleaner",
      "Illumination",
      "Magic",
      "MagicalShield",
      "Mind Control",
      "SilverLEGODestruction",
      "Target"
    ],
    "voiceActor": "Ralph Fiennes",
    "minifigure": {
      "legoId": "dim032",
      "imageUrl": "https://img.bricklink.com/ItemImage/MN/0/dim032.png",
      "dimensionsId": "dim032",
      "bricklinkId": "unknown",
      "imageUrls": [
        {
          "url": "https://img.bricklink.com/ItemImage/MN/0/dim032.png",
          "type": "minifig"
        }
      ]
    },
    "adventureWorld": "unknown",
    "aliases": [],
    "availabilityStatus": "unknown"
  },
  {
    "name": "Lumpy Space Princess",
    "franchise": "Adventure Time",
    "pack": {
      "type": "Team",
      "name": "Adventure Time Team Pack",
      "releaseWave": 2,
      "setNumber": "unknown",
      "releaseDate": "unknown"
    },
    "abilities": [
      "Boomerang",
      "Flight",
      "HazardProtection",
      "Rainbow LEGO Objects",
      "SlurpAccess",
      "Target"
    ],
    "voiceActor": "Pendleton Ward",
    "minifigure": {
      "legoId": null,
      "imageUrl": "unknown",
      "dimensionsId": "unknown",
      "bricklinkId": "unknown",
      "imageUrls": []
    },
    "adventureWorld": "unknown",
    "aliases": [],
    "availabilityStatus": "unknown"
  },
  {
    "name": "Marceline",
    "franchise": "unknown",
    "pack": {
      "type": "unknown",
      "name": "unknown",
      "releaseWave": null,
      "setNumber": "71285",
      "releaseDate": "unknown"
    },
    "abilities": [
      "Acrobat",
      "Flight",
      "HeartRegeneration",
      "MindControl",
      "MiniAccess",
      "RopeSwing",
      "Stealth",
      "Tracking",
      "VineCut"
    ],
    "voiceActor": "unknown",
    "minifigure": {
      "legoId": null,
      "imageUrl": "unknown",
      "dimensionsId": "unknown",
      "bricklinkId": "unknown",
      "imageUrls": []
    },
    "adventureWorld": "unknown",
    "aliases": [],
    "availabilityStatus": "unknown"
  },
  {
    "name": "Marty McFly",
    "franchise": "Back to the Future",
    "pack": {
      "type": "Level",
      "name": "Back to the Future Level Pack",
      "releaseWave": 1,
      "setNumber": "71201",
      "releaseDate": "unknown"
    },
    "abilities": [],
    "voiceActor": "Michael J. Fox",
    "minifigure": {
      "legoId": "dim004pb01",
      "imageUrl": "https://img.bricklink.com/ItemImage/MN/0/dim004pb01.png",
      "dimensionsId": "dim004pb01",
      "bricklinkId": "unknown",
      "imageUrls": [
        {
          "url": "https://img.bricklink.com/ItemImage/MN/0/dim004pb01.png",
          "type": "minifig"
        }
      ]
    },
    "adventureWorld": "unknown",
    "aliases": [],
    "availabilityStatus": "unknown"
  },
  {
    "name": "Michael Knight",
    "franchise": "Knight Rider",
    "pack": {
      "type": "Fun",
      "name": "Knight Rider Fun Pack",
      "releaseWave": 2,
      "setNumber": "71286",
      "releaseDate": "unknown"
    },
    "abilities": [
      "Technology",
      "Tracking",
      "XRayVision"
    ],
    "voiceActor": "Nick Offerman",
    "minifigure": {
      "legoId": "dim045",
      "imageUrl": "https://img.bricklink.com/ItemImage/MN/0/dim045.png",
      "dimensionsId": "dim045",
      "bricklinkId": "unknown",
      "imageUrls": [
        {
          "url": "https://img.bricklink.com/ItemImage/MN/0/dim045.png",
          "type": "minifig"
        }
      ]
    },
    "adventureWorld": "unknown",
    "aliases": [],
    "availabilityStatus": "unknown"
  },
  {
    "name": "Newt Scamander",
    "franchise": "Fantastic Beasts",
    "pack": {
      "type": "Story",
      "name": "Fantastic Beasts Story Pack",
      "releaseWave": 2,
      "setNumber": "71253",
      "releaseDate": "unknown"
    },
    "abilities": [
      "CharacterChanging",
      "FixIt",
      "Growth",
      "Intelligence",
      "LaserDeflector",
      "Magic",
      "MagicalShield",
      "Technology"
    ],
    "voiceActor": "Eddie Redmayne",
    "minifigure": {
      "legoId": "dim034",
      "imageUrl": "https://img.bricklink.com/ItemImage/MN/0/dim034.png",
      "dimensionsId": "dim034",
      "bricklinkId": "unknown",
      "imageUrls": [
        {
          "url": "https://img.bricklink.com/ItemImage/MN/0/dim034.png",
          "type": "minifig"
        }
      ]
    },
    "adventureWorld": "unknown",
    "aliases": [],
    "availabilityStatus": "unknown"
  },
  {
    "name": "Nya",
    "franchise": "Ninjago",
    "pack": {
      "type": "Fun",
      "name": "Nya Fun Pack",
      "releaseWave": 1,
      "setNumber": "71216",
      "releaseDate": "unknown"
    },
    "abilities": [
      "Acrobat",
      "Fix-It",
      "Spinjitzu",
      "Stealth"
    ],
    "voiceActor": "Kelly Metzger",
    "minifigure": {
      "legoId": "dim016pb01",
      "imageUrl": "https://img.bricklink.com/ItemImage/MN/0/dim016pb01.png",
      "dimensionsId": "dim016pb01",
      "bricklinkId": "unknown",
      "imageUrls": [
        {
          "url": "https://img.bricklink.com/ItemImage/MN/0/dim016pb01.png",
          "type": "minifig"
        }
      ]
    },
    "adventureWorld": "unknown",
    "aliases": [],
    "availabilityStatus": "unknown"
  },
  {
    "name": "Owen Grady",
    "franchise": "Jurassic World",
    "pack": {
      "type": "Team",
      "name": "Jurassic World Team Pack",
      "releaseWave": 1,
      "setNumber": "71205",
      "releaseDate": "unknown"
    },
    "abilities": [],
    "voiceActor": "Chris Pratt",
    "minifigure": {
      "legoId": "dim005pb01",
      "imageUrl": "https://img.bricklink.com/ItemImage/MN/0/dim005pb01.png",
      "dimensionsId": "dim005pb01",
      "bricklinkId": "unknown",
      "imageUrls": [
        {
          "url": "https://img.bricklink.com/ItemImage/MN/0/dim005pb01.png",
          "type": "minifig"
        }
      ]
    },
    "adventureWorld": "unknown",
    "aliases": [],
    "availabilityStatus": "unknown"
  },
  {
    "name": "Peter Venkman",
    "franchise": "Ghostbusters",
    "pack": {
      "type": "Level",
      "name": "Ghostbusters Level Pack",
      "releaseWave": 1,
      "setNumber": "71228",
      "releaseDate": "unknown"
    },
    "abilities": [
      "CharacterChanging",
      "Hazard Protection",
      "HazardProtection",
      "Laser",
      "Suspend Ghost"
    ],
    "voiceActor": "Bill Murray",
    "minifigure": {
      "legoId": "dim019pb01",
      "imageUrl": "https://img.bricklink.com/ItemImage/MN/0/dim019pb01.png",
      "dimensionsId": "dim019pb01",
      "bricklinkId": "unknown",
      "imageUrls": [
        {
          "url": "https://img.bricklink.com/ItemImage/MN/0/dim019pb01.png",
          "type": "minifig"
        }
      ]
    },
    "adventureWorld": "unknown",
    "aliases": [],
    "availabilityStatus": "unknown"
  },
  {
    "name": "Raven",
    "franchise": "Teen Titans Go!",
    "pack": {
      "type": "Team",
      "name": "Teen Titans Go! Team Pack",
      "releaseWave": 2,
      "setNumber": "unknown",
      "releaseDate": "unknown"
    },
    "abilities": [
      "Electricity",
      "Flight",
      "Magic",
      "MagicalShield"
    ],
    "voiceActor": "Tara Strong",
    "minifigure": {
      "legoId": "dim048",
      "imageUrl": "https://img.bricklink.com/ItemImage/MN/0/dim048.png",
      "dimensionsId": "dim048",
      "bricklinkId": "unknown",
      "imageUrls": [
        {
          "url": "https://img.bricklink.com/ItemImage/MN/0/dim048.png",
          "type": "minifig"
        }
      ]
    },
    "adventureWorld": "unknown",
    "aliases": [],
    "availabilityStatus": "unknown"
  },
  {
    "name": "Robin",
    "franchise": "The LEGO Batman Movie",
    "pack": {
      "type": "Story",
      "name": "The LEGO Batman Movie Story Pack",
      "releaseWave": 2,
      "setNumber": "71264",
      "releaseDate": "unknown"
    },
    "abilities": [
      "Acrobat",
      "Grapple",
      "Stealth"
    ],
    "voiceActor": "Michael Cera",
    "minifigure": {
      "legoId": "dim041",
      "imageUrl": "https://img.bricklink.com/ItemImage/MN/0/dim041.png",
      "dimensionsId": "dim041",
      "bricklinkId": "unknown",
      "imageUrls": [
        {
          "url": "https://img.bricklink.com/ItemImage/MN/0/dim041.png",
          "type": "minifig"
        }
      ]
    },
    "aliases": [
      "Robin (LBM)"
    ],
    "adventureWorld": "unknown",
    "availabilityStatus": "unknown"
  },
  {
    "name": "Scooby-Doo",
    "franchise": "Scooby-Doo",
    "pack": {
      "type": "Team",
      "name": "Scooby-Doo Team Pack",
      "releaseWave": 1,
      "setNumber": "71206",
      "releaseDate": "unknown"
    },
    "abilities": [
      "Dig",
      "Dive",
      "Glide",
      "Stealth",
      "Tracking"
    ],
    "voiceActor": "Frank Welker",
    "minifigure": {
      "legoId": "dim007pb01",
      "imageUrl": "https://img.bricklink.com/ItemImage/MN/0/dim007pb01.png",
      "dimensionsId": "dim007pb01",
      "bricklinkId": "unknown",
      "imageUrls": [
        {
          "url": "https://img.bricklink.com/ItemImage/MN/0/dim007pb01.png",
          "type": "minifig"
        }
      ]
    },
    "adventureWorld": "unknown",
    "aliases": [],
    "availabilityStatus": "unknown"
  },
  {
    "name": "Sensei Wu",
    "franchise": "Ninjago",
    "pack": {
      "type": "Fun",
      "name": "Sensei Wu Fun Pack",
      "releaseWave": 1,
      "setNumber": "unknown",
      "releaseDate": "unknown"
    },
    "abilities": [
      "Acrobat",
      "Pole Vault",
      "Spinjitzu",
      "Stealth"
    ],
    "voiceActor": "Paul Dobson",
    "minifigure": {
      "legoId": "dim015pb01",
      "imageUrl": "https://img.bricklink.com/ItemImage/MN/0/dim015pb01.png",
      "dimensionsId": "dim015pb01",
      "bricklinkId": "unknown",
      "imageUrls": [
        {
          "url": "https://img.bricklink.com/ItemImage/MN/0/dim015pb01.png",
          "type": "minifig"
        }
      ]
    },
    "adventureWorld": "unknown",
    "aliases": [],
    "availabilityStatus": "unknown"
  },
  {
    "name": "Shaggy",
    "franchise": "Scooby-Doo",
    "pack": {
      "type": "Team",
      "name": "Scooby-Doo Team Pack",
      "releaseWave": 1,
      "setNumber": "71206",
      "releaseDate": "unknown"
    },
    "abilities": [
      "Illumination",
      "Stealth",
      "Tracking"
    ],
    "voiceActor": "Matthew Lillard",
    "minifigure": {
      "legoId": "dim008pb01",
      "imageUrl": "https://img.bricklink.com/ItemImage/MN/0/dim008pb01.png",
      "dimensionsId": "dim008pb01",
      "bricklinkId": "unknown",
      "imageUrls": [
        {
          "url": "https://img.bricklink.com/ItemImage/MN/0/dim008pb01.png",
          "type": "minifig"
        }
      ]
    },
    "adventureWorld": "unknown",
    "aliases": [],
    "availabilityStatus": "unknown"
  },
  {
    "name": "Slimer",
    "franchise": "Ghostbusters",
    "pack": {
      "type": "Fun",
      "name": "Slimer Fun Pack",
      "releaseWave": 1,
      "setNumber": "71241",
      "releaseDate": "unknown"
    },
    "abilities": [
      "Boomerang",
      "Dive",
      "Flight",
      "Flying",
      "Hazard Cleaner",
      "Hazard Protection",
      "HazardCleaner",
      "HazardProtection",
      "Illumination",
      "Invulnerability",
      "Mini Access",
      "Sonar Smash",
      "SonarSmash"
    ],
    "voiceActor": "Frank Welker",
    "minifigure": {
      "legoId": "dim021pb01",
      "imageUrl": "https://img.bricklink.com/ItemImage/MN/0/dim021pb01.png",
      "dimensionsId": "dim021pb01",
      "bricklinkId": "unknown",
      "imageUrls": [
        {
          "url": "https://img.bricklink.com/ItemImage/MN/0/dim021pb01.png",
          "type": "minifig"
        }
      ]
    },
    "adventureWorld": "unknown",
    "aliases": [],
    "availabilityStatus": "unknown"
  },
  {
    "name": "Sloth",
    "franchise": "The Goonies",
    "pack": {
      "type": "Level",
      "name": "The Goonies Level Pack",
      "releaseWave": 2,
      "setNumber": "71267",
      "releaseDate": "unknown"
    },
    "abilities": [
      "Dive",
      "Grapple",
      "RopeSwing",
      "SuperStrength",
      "Tracking"
    ],
    "voiceActor": "unknown",
    "minifigure": {
      "legoId": "dim046",
      "imageUrl": "https://img.bricklink.com/ItemImage/MN/0/dim046.png",
      "dimensionsId": "dim046",
      "bricklinkId": "unknown",
      "imageUrls": [
        {
          "url": "https://img.bricklink.com/ItemImage/MN/0/dim046.png",
          "type": "minifig"
        }
      ]
    },
    "adventureWorld": "unknown",
    "aliases": [],
    "availabilityStatus": "unknown"
  },
  {
    "name": "Sonic the Hedgehog",
    "franchise": "Sonic the Hedgehog",
    "pack": {
      "type": "Level",
      "name": "Sonic the Hedgehog Level Pack",
      "releaseWave": 2,
      "setNumber": "71244",
      "releaseDate": "unknown"
    },
    "abilities": [
      "Acrobat",
      "Speed",
      "SuperSpeed",
      "SuperStrength"
    ],
    "voiceActor": "Roger Craig Smith",
    "minifigure": {
      "legoId": "dim039",
      "imageUrl": "https://img.bricklink.com/ItemImage/MN/0/dim039.png",
      "dimensionsId": "dim039",
      "bricklinkId": "unknown",
      "imageUrls": [
        {
          "url": "https://img.bricklink.com/ItemImage/MN/0/dim039.png",
          "type": "minifig"
        }
      ]
    },
    "adventureWorld": "unknown",
    "aliases": [],
    "availabilityStatus": "unknown"
  },
  {
    "name": "Starfire",
    "franchise": "Teen Titans Go!",
    "pack": {
      "type": "Fun",
      "name": "Teen Titans Go! Fun Pack",
      "releaseWave": 2,
      "setNumber": "unknown",
      "releaseDate": "unknown"
    },
    "abilities": [
      "Flight",
      "HeartRegeneration",
      "LEGOConstructs",
      "Laser"
    ],
    "voiceActor": "Hynden Walch",
    "minifigure": {
      "legoId": "dim050",
      "imageUrl": "https://img.bricklink.com/ItemImage/MN/0/dim050.png",
      "dimensionsId": "dim050",
      "bricklinkId": "unknown",
      "imageUrls": [
        {
          "url": "https://img.bricklink.com/ItemImage/MN/0/dim050.png",
          "type": "minifig"
        }
      ]
    },
    "adventureWorld": "unknown",
    "aliases": [],
    "availabilityStatus": "unknown"
  },
  {
    "name": "Stay Puft",
    "franchise": "Ghostbusters",
    "pack": {
      "type": "Fun",
      "name": "Stay Puft Fun Pack",
      "releaseWave": 1,
      "setNumber": "71233",
      "releaseDate": "unknown"
    },
    "abilities": [
      "Big Transform",
      "BigTransform",
      "Hazard Protection",
      "Super Strength",
      "SuperStrength"
    ],
    "voiceActor": "unknown",
    "minifigure": {
      "legoId": "dim020pb01",
      "imageUrl": "https://img.bricklink.com/ItemImage/MN/0/dim020pb01.png",
      "dimensionsId": "dim020pb01",
      "bricklinkId": "unknown",
      "imageUrls": [
        {
          "url": "https://img.bricklink.com/ItemImage/MN/0/dim020pb01.png",
          "type": "minifig"
        }
      ]
    },
    "adventureWorld": "unknown",
    "aliases": [],
    "availabilityStatus": "unknown"
  },
  {
    "name": "Stripe",
    "franchise": "Gremlins",
    "pack": {
      "type": "Team",
      "name": "Gremlins Team Pack",
      "releaseWave": 2,
      "setNumber": "71256",
      "releaseDate": "unknown"
    },
    "abilities": [
      "Acrobat"
    ],
    "voiceActor": "Frank Welker",
    "minifigure": {
      "legoId": "dim037",
      "imageUrl": "https://img.bricklink.com/ItemImage/MN/0/dim037.png",
      "dimensionsId": "dim037",
      "bricklinkId": "unknown",
      "imageUrls": [
        {
          "url": "https://img.bricklink.com/ItemImage/MN/0/dim037.png",
          "type": "minifig"
        }
      ]
    },
    "adventureWorld": "unknown",
    "aliases": [],
    "availabilityStatus": "unknown"
  },
  {
    "name": "Superman",
    "franchise": "DC Comics",
    "pack": {
      "type": "Fun",
      "name": "Superman Fun Pack",
      "releaseWave": 1,
      "setNumber": "71236",
      "releaseDate": "unknown"
    },
    "abilities": [
      "Dive",
      "Flight",
      "Flying",
      "Invulnerability",
      "Laser",
      "Super Strength",
      "SuperStrength",
      "X-Ray Vision",
      "XRayVision"
    ],
    "voiceActor": "Travis Willingham",
    "minifigure": {
      "legoId": "dim022pb01",
      "imageUrl": "https://img.bricklink.com/ItemImage/MN/0/dim022pb01.png",
      "dimensionsId": "dim022pb01",
      "bricklinkId": "unknown",
      "imageUrls": [
        {
          "url": "https://img.bricklink.com/ItemImage/MN/0/dim022pb01.png",
          "type": "minifig"
        }
      ]
    },
    "adventureWorld": "unknown",
    "aliases": [],
    "availabilityStatus": "unknown"
  },
  {
    "name": "Tina Goldstein",
    "franchise": "Fantastic Beasts",
    "pack": {
      "type": "Fun",
      "name": "Tina Goldstein Fun Pack",
      "releaseWave": 2,
      "setNumber": "71257",
      "releaseDate": "unknown"
    },
    "abilities": [
      "Acrobat",
      "CharacterChanging",
      "LaserDeflector",
      "Magic",
      "MagicalShield",
      "SilverLEGODestruction",
      "Target",
      "WaterSpray"
    ],
    "voiceActor": "Katherine Waterston",
    "minifigure": {
      "legoId": "dim035",
      "imageUrl": "https://img.bricklink.com/ItemImage/MN/0/dim035.png",
      "dimensionsId": "dim035",
      "bricklinkId": "unknown",
      "imageUrls": [
        {
          "url": "https://img.bricklink.com/ItemImage/MN/0/dim035.png",
          "type": "minifig"
        }
      ]
    },
    "adventureWorld": "unknown",
    "aliases": [],
    "availabilityStatus": "unknown"
  },
  {
    "name": "Unikitty",
    "franchise": "The LEGO Movie",
    "pack": {
      "type": "Fun",
      "name": "Unikitty Fun Pack",
      "releaseWave": 1,
      "setNumber": "71231",
      "releaseDate": "unknown"
    },
    "abilities": [
      "Big Transform",
      "BigTransform",
      "Master Build",
      "Rainbow LEGO Objects",
      "RainbowLEGOObjects",
      "SuperStrength"
    ],
    "voiceActor": "Alison Brie",
    "minifigure": {
      "legoId": "dim010",
      "imageUrl": "https://img.bricklink.com/ItemImage/MN/0/dim010.png",
      "dimensionsId": "dim010",
      "bricklinkId": "unknown",
      "imageUrls": [
        {
          "url": "https://img.bricklink.com/ItemImage/MN/0/dim010.png",
          "type": "minifig"
        }
      ]
    },
    "adventureWorld": "unknown",
    "aliases": [],
    "availabilityStatus": "unknown"
  },
  {
    "name": "Wicked Witch",
    "franchise": "The Wizard of Oz",
    "pack": {
      "type": "Fun",
      "name": "Wicked Witch Fun Pack",
      "releaseWave": 1,
      "setNumber": "71221",
      "releaseDate": "unknown"
    },
    "abilities": [
      "Flight",
      "Flying",
      "Illumination",
      "Magic",
      "Magical Shield",
      "MagicalShield",
      "Mind Control",
      "MindControl",
      "Silver LEGO Blowup",
      "SilverLEGODestruction"
    ],
    "voiceActor": "Courtenay Taylor",
    "minifigure": {
      "legoId": "dim011",
      "imageUrl": "https://img.bricklink.com/ItemImage/MN/0/dim011.png",
      "dimensionsId": "dim011",
      "bricklinkId": "unknown",
      "imageUrls": [
        {
          "url": "https://img.bricklink.com/ItemImage/MN/0/dim011.png",
          "type": "minifig"
        }
      ]
    },
    "aliases": [
      "Wicked Witch of the West"
    ],
    "adventureWorld": "unknown",
    "availabilityStatus": "unknown"
  },
  {
    "name": "Wonder Woman",
    "franchise": "DC Comics",
    "pack": {
      "type": "Fun",
      "name": "Wonder Woman Fun Pack",
      "releaseWave": 1,
      "setNumber": "71209",
      "releaseDate": "unknown"
    },
    "abilities": [
      "Acrobat",
      "Boomerang",
      "Dive",
      "Flight",
      "Invulnerability",
      "XRayVision"
    ],
    "voiceActor": "Laura Bailey",
    "minifigure": {
      "legoId": "dim006pb01",
      "imageUrl": "https://img.bricklink.com/ItemImage/MN/0/dim006pb01.png",
      "dimensionsId": "dim006pb01",
      "bricklinkId": "unknown",
      "imageUrls": [
        {
          "url": "https://img.bricklink.com/ItemImage/MN/0/dim006pb01.png",
          "type": "minifig"
        }
      ]
    },
    "adventureWorld": "unknown",
    "aliases": [],
    "availabilityStatus": "unknown"
  },
  {
    "name": "Zane",
    "franchise": "Ninjago",
    "pack": {
      "type": "Fun",
      "name": "Zane Fun Pack",
      "releaseWave": 1,
      "setNumber": "71217",
      "releaseDate": "unknown"
    },
    "abilities": [
      "Acrobat",
      "Boomerang",
      "Dive",
      "Spinjitzu",
      "Stealth",
      "X-Ray Vision",
      "XRayVision"
    ],
    "voiceActor": "Brent Miller",
    "minifigure": {
      "legoId": "dim014pb01",
      "imageUrl": "https://img.bricklink.com/ItemImage/MN/0/dim014pb01.png",
      "dimensionsId": "dim014pb01",
      "bricklinkId": "unknown",
      "imageUrls": [
        {
          "url": "https://img.bricklink.com/ItemImage/MN/0/dim014pb01.png",
          "type": "minifig"
        }
      ]
    },
    "adventureWorld": "unknown",
    "aliases": [],
    "availabilityStatus": "unknown"
  },
  {
    "name": "Green Arrow",
    "franchise": "DC Comics",
    "pack": {
      "type": "unknown",
      "name": "Green Arrow Polybag",
      "releaseWave": null,
      "setNumber": "71342",
      "releaseDate": "2016"
    },
    "abilities": [
      "Acrobat",
      "Grapple",
      "Pole Vault",
      "Target"
    ],
    "voiceActor": "unknown",
    "minifigure": {
      "legoId": null,
      "imageUrl": "https://img.bricklink.com/ItemImage/MN/0/sh0153.png",
      "dimensionsId": "unknown",
      "bricklinkId": "sh0153",
      "imageUrls": [
        {
          "url": "https://img.bricklink.com/ItemImage/MN/0/sh0153.png",
          "type": "minifig"
        }
      ]
    },
    "adventureWorld": "DC Comics",
    "aliases": [],
    "availabilityStatus": "unknown"
  },
  {
    "name": "Supergirl",
    "franchise": "unknown",
    "pack": {
      "type": "unknown",
      "name": "unknown",
      "releaseWave": null,
      "setNumber": "71340",
      "releaseDate": "unknown"
    },
    "abilities": [
      "Dig",
      "Dive",
      "Flight",
      "Flying",
      "Grapple",
      "Invulnerability",
      "LEGOConstructs",
      "Laser",
      "SuperStrength",
      "XRayVision"
    ],
    "voiceActor": "unknown",
    "minifigure": {
      "legoId": null,
      "imageUrl": "unknown",
      "dimensionsId": "unknown",
      "bricklinkId": "unknown",
      "imageUrls": []
    },
    "adventureWorld": "unknown",
    "aliases": [],
    "availabilityStatus": "unknown"
  }
]